eurlex2lexparency/__init__.py
eurlex2lexparency/etl.py
eurlex2lexparency/etl_manager.py
eurlex2lexparency/celex_manager/__init__.py
eurlex2lexparency/celex_manager/celex.py
eurlex2lexparency/celex_manager/doQuery_envelope_template.xml
eurlex2lexparency/celex_manager/dummy.py
eurlex2lexparency/celex_manager/eurlex.py
eurlex2lexparency/celex_manager/exec.py
eurlex2lexparency/celex_manager/get_missed.py
eurlex2lexparency/celex_manager/legislation_getter.py
eurlex2lexparency/celex_manager/model.py
eurlex2lexparency/celex_manager/reference_sanitizer.py
eurlex2lexparency/celex_manager/update_in_force.py
eurlex2lexparency/celex_manager/sparql_templates/act.sparql
eurlex2lexparency/celex_manager/sparql_templates/act_consolidates.sparql
eurlex2lexparency/celex_manager/sparql_templates/celex_in_force.sparql
eurlex2lexparency/celex_manager/sparql_templates/celexes_inter_year.sparql
eurlex2lexparency/celex_manager/sparql_templates/changes_year.sparql
eurlex2lexparency/celex_manager/sparql_templates/cons_celex_lang.sparql
eurlex2lexparency/celex_manager/sparql_templates/consleg.sparql
eurlex2lexparency/celex_manager/sparql_templates/corr_celex_lang.sparql
eurlex2lexparency/celex_manager/sparql_templates/corrigenda.sparql
eurlex2lexparency/celex_manager/sparql_templates/deforce_repealed.sparql
eurlex2lexparency/celex_manager/sparql_templates/in_force_for.sparql
eurlex2lexparency/celex_manager/sparql_templates/missed_consolidates.sparql
eurlex2lexparency/celex_manager/sparql_templates/recent_corrigenda_per_type.sparql
eurlex2lexparency/extraction/__init__.py
eurlex2lexparency/extraction/generic.py
eurlex2lexparency/extraction/full_bodies/__init__.py
eurlex2lexparency/extraction/full_bodies/dummy.py
eurlex2lexparency/extraction/full_bodies/formex.py
eurlex2lexparency/extraction/full_bodies/html.py
eurlex2lexparency/extraction/full_bodies/pdf.py
eurlex2lexparency/extraction/meta_data/__init__.py
eurlex2lexparency/extraction/meta_data/cdm_data.py
eurlex2lexparency-1.3.dist-info/LICENSE
eurlex2lexparency-1.3.dist-info/METADATA
eurlex2lexparency-1.3.dist-info/WHEEL
eurlex2lexparency-1.3.dist-info/top_level.txt
eurlex2lexparency-1.3.dist-info/RECORD
